SearchMusic/__init__.py
SearchMusic-0.0.2.dist-info/LICENSE
SearchMusic-0.0.2.dist-info/METADATA
SearchMusic-0.0.2.dist-info/WHEEL
SearchMusic-0.0.2.dist-info/top_level.txt
SearchMusic-0.0.2.dist-info/RECORD
