Metadata-Version: 2.1
Name: SearchMusic
Version: 0.0.2
Summary: Library to search and download your favorite songs in the best quality :)
Home-page: https://github.com/DrSudoSaeed
Author: SudoSaeed
Author-email: DrSudoSaeed@gmail.com
License: UNKNOWN
Project-URL: Bug Tracker, https://github.com/DrSudoSaeed/
Platform: UNKNOWN
Classifier: Programming Language :: Python :: 3
Classifier: License :: OSI Approved :: MIT License
Classifier: Operating System :: OS Independent
Requires-Python: >=3.6
License-File: LICENSE
